odoo/addons/business_requirement_crm/README.rst
odoo/addons/business_requirement_crm/__init__.py
odoo/addons/business_requirement_crm/__manifest__.py
odoo/addons/business_requirement_crm/i18n/business_requirement_crm.pot
odoo/addons/business_requirement_crm/i18n/es.po
odoo/addons/business_requirement_crm/models/__init__.py
odoo/addons/business_requirement_crm/models/business_requirement.py
odoo/addons/business_requirement_crm/models/crm_lead.py
odoo/addons/business_requirement_crm/readme/CONTRIBUTORS.rst
odoo/addons/business_requirement_crm/readme/DESCRIPTION.rst
odoo/addons/business_requirement_crm/readme/USAGE.rst
odoo/addons/business_requirement_crm/static/description/icon.png
odoo/addons/business_requirement_crm/static/description/index.html
odoo/addons/business_requirement_crm/tests/__init__.py
odoo/addons/business_requirement_crm/tests/test_business_requirement_crm.py
odoo/addons/business_requirement_crm/views/business_requirement_views.xml
odoo/addons/business_requirement_crm/views/crm_lead_views.xml
odoo/addons/business_requirement_crm/wizard/__init__.py
odoo/addons/business_requirement_crm/wizard/crm_lead_convert_to_requirement.py
odoo/addons/business_requirement_crm/wizard/crm_lead_convert_to_requirement_views.xml
odoo11_addon_business_requirement_crm-11.0.1.1.0.dist-info/METADATA
odoo11_addon_business_requirement_crm-11.0.1.1.0.dist-info/WHEEL
odoo11_addon_business_requirement_crm-11.0.1.1.0.dist-info/top_level.txt
odoo11_addon_business_requirement_crm-11.0.1.1.0.dist-info/RECORD
